yunhulink/__init__.py
yunhulink/functional.py
yunhulink/listen.py
yunhulink/orm.py
yunhulink/streamkit.py
YunhuLink-1.0.2.dist-info/LICENSE
YunhuLink-1.0.2.dist-info/METADATA
YunhuLink-1.0.2.dist-info/WHEEL
YunhuLink-1.0.2.dist-info/top_level.txt
YunhuLink-1.0.2.dist-info/RECORD
