Metadata-Version: 2.1
Name: YunhuLink
Version: 1.0.2
Summary: An third-party SDK of yunhu chat.
Author: Li lingyi
Author-email: alan_sudo@yeah.net
Maintainer: Project VsingerXiaoice Group
Maintainer-email: alan_sudo@yeah.net
License: Creative Commons Legal Code
Requires: fastapi
Requires: pydantic
Requires: aiohttp
Requires: uvicorn
License-File: LICENSE
